intelligence/__init__.py
intelligence/language/__init__.py
intelligence/language/__main__.py
intelligence/sound/__init__.py
intelligence/speech/__init__.py
intelligence/vision/__init__.py
humaan_intelligence-0.0.0a0.dist-info/LICENSE
humaan_intelligence-0.0.0a0.dist-info/METADATA
humaan_intelligence-0.0.0a0.dist-info/WHEEL
humaan_intelligence-0.0.0a0.dist-info/top_level.txt
humaan_intelligence-0.0.0a0.dist-info/RECORD
