Metadata-Version: 2.1
Name: humaan-intelligence
Version: 0.0.0a0
Summary: Humaan Intelligence Client Library for Python
Author-email: Humaan <support@humaan.ai>
License: Apache License 2.0
Project-URL: Homepage, https://github.com/humaan-ai/intelligence-python-sdk
Project-URL: Documentation, https://developer.humaan.ai/docs/intelligence
Project-URL: Bug Tracker, https://github.com/humaan-ai/intelligence-python-sdk/issues
Classifier: Development Status :: 1 - Planning
Classifier: Intended Audience :: Developers
Classifier: License :: OSI Approved :: Apache Software License
Classifier: Operating System :: OS Independent
Classifier: Programming Language :: Python
Classifier: Programming Language :: Python :: 3
Classifier: Programming Language :: Python :: 3.7
Classifier: Programming Language :: Python :: 3.8
Classifier: Programming Language :: Python :: 3.9
Classifier: Topic :: Scientific/Engineering :: Artificial Intelligence
Requires-Python: >=3.7.0
License-File: LICENSE
